<?xml version='1.0' encoding='UTF-8' ?>

<statuses version='1.0'>
	<status name='Auto-Cached' transient='true' created='1381861800' lastused='1381861800' usage_count='1'>
		<state>available</state>
		<substatus>
			<account protocol='prpl-sipe'>john.harris@imail.org,co\lpjharri</account>
			<state>available</state>
		</substatus>
	</status>
	<status name='Auto-Cached' transient='true' created='1381860000' lastused='1381860000' usage_count='1'>
		<state>unavailable</state>
		<substatus>
			<account protocol='prpl-sipe'>john.harris@imail.org,co\lpjharri</account>
			<state>busy</state>
		</substatus>
	</status>
	<status name='Auto-Cached' transient='true' created='1381858200' lastused='1381858200' usage_count='1'>
		<state>available</state>
		<substatus>
			<account protocol='prpl-sipe'>john.harris@imail.org,co\lpjharri</account>
			<state>available</state>
		</substatus>
	</status>
	<status name='Auto-Cached' transient='true' created='1381856400' lastused='1381856400' usage_count='1'>
		<state>unavailable</state>
		<substatus>
			<account protocol='prpl-sipe'>john.harris@imail.org,co\lpjharri</account>
			<state>busy</state>
		</substatus>
	</status>
	<status name='Auto-Cached' transient='true' created='1381852800' lastused='1381852800' usage_count='1'>
		<state>available</state>
		<substatus>
			<account protocol='prpl-sipe'>john.harris@imail.org,co\lpjharri</account>
			<state>available</state>
		</substatus>
	</status>
	<status name='Auto-Cached' transient='true' created='1381851000' lastused='1381851000' usage_count='1'>
		<state>unavailable</state>
		<substatus>
			<account protocol='prpl-sipe'>john.harris@imail.org,co\lpjharri</account>
			<state>busy</state>
		</substatus>
	</status>
	<status name='Auto-Cached' transient='true' created='1381795910' lastused='1381795910' usage_count='1'>
		<state>available</state>
		<substatus>
			<account protocol='prpl-sipe'>john.harris@imail.org,co\lpjharri</account>
			<state>available</state>
		</substatus>
	</status>
	<status name='Auto-Cached' transient='true' created='1381780503' lastused='1381780503' usage_count='1'>
		<state>unavailable</state>
		<substatus>
			<account protocol='prpl-sipe'>john.harris@imail.org,co\lpjharri</account>
			<state>busy</state>
		</substatus>
	</status>
	<status name='Auto-Cached' transient='true' created='1381525202' lastused='1381525202' usage_count='1'>
		<state>available</state>
		<substatus>
			<account protocol='prpl-sipe'>john.harris@imail.org,co\lpjharri</account>
			<state>available</state>
		</substatus>
	</status>
	<status name='Auto-Cached' transient='true' created='1381523404' lastused='1381523404' usage_count='1'>
		<state>unavailable</state>
		<substatus>
			<account protocol='prpl-sipe'>john.harris@imail.org,co\lpjharri</account>
			<state>busy</state>
		</substatus>
	</status>
	<status name='Auto-Cached' transient='true' created='1381521602' lastused='1381521602' usage_count='1'>
		<state>available</state>
		<substatus>
			<account protocol='prpl-sipe'>john.harris@imail.org,co\lpjharri</account>
			<state>available</state>
		</substatus>
	</status>
	<status name='Auto-Cached' transient='true' created='1381519801' lastused='1381519801' usage_count='1'>
		<state>unavailable</state>
		<substatus>
			<account protocol='prpl-sipe'>john.harris@imail.org,co\lpjharri</account>
			<state>busy</state>
		</substatus>
	</status>
	<status name='Auto-Cached' transient='true' created='1381438800' lastused='1381438800' usage_count='1'>
		<state>available</state>
		<substatus>
			<account protocol='prpl-sipe'>john.harris@imail.org,co\lpjharri</account>
			<state>available</state>
		</substatus>
	</status>
	<status name='Auto-Cached' transient='true' created='1381435200' lastused='1381435200' usage_count='1'>
		<state>unavailable</state>
		<substatus>
			<account protocol='prpl-sipe'>john.harris@imail.org,co\lpjharri</account>
			<state>busy</state>
		</substatus>
	</status>
	<status name='Auto-Cached' transient='true' created='1381410342' lastused='1381410342' usage_count='1'>
		<state>available</state>
		<substatus>
			<account protocol='prpl-sipe'>john.harris@imail.org,co\lpjharri</account>
			<state>available</state>
		</substatus>
	</status>
	<status name='Auto-Cached' transient='true' created='1381356000' lastused='1381356000' usage_count='1'>
		<state>unavailable</state>
		<substatus>
			<account protocol='prpl-sipe'>john.harris@imail.org,co\lpjharri</account>
			<state>busy</state>
		</substatus>
	</status>
	<status name='Auto-Cached' transient='true' created='1381341600' lastused='1381341600' usage_count='1'>
		<state>available</state>
		<substatus>
			<account protocol='prpl-sipe'>john.harris@imail.org,co\lpjharri</account>
			<state>available</state>
		</substatus>
	</status>
	<status name='Auto-Cached' transient='true' created='1381338983' lastused='1381338983' usage_count='1'>
		<state>unavailable</state>
		<substatus>
			<account protocol='prpl-sipe'>john.harris@imail.org,co\lpjharri</account>
			<state>busy</state>
		</substatus>
	</status>
	<status name='Auto-Cached' transient='true' created='1381338922' lastused='1381338922' usage_count='1'>
		<state>available</state>
		<substatus>
			<account protocol='prpl-sipe'>john.harris@imail.org,co\lpjharri</account>
			<state>available</state>
		</substatus>
	</status>
	<status name='Auto-Cached' transient='true' created='1381334400' lastused='1381334400' usage_count='1'>
		<state>unavailable</state>
		<substatus>
			<account protocol='prpl-sipe'>john.harris@imail.org,co\lpjharri</account>
			<state>busy</state>
		</substatus>
	</status>
	<status name='Auto-Cached' transient='true' created='1381183200' lastused='1381183200' usage_count='1'>
		<state>available</state>
		<substatus>
			<account protocol='prpl-sipe'>john.harris@imail.org,co\lpjharri</account>
			<state>available</state>
		</substatus>
	</status>
	<status name='Auto-Cached' transient='true' created='1381179600' lastused='1381179600' usage_count='1'>
		<state>unavailable</state>
		<substatus>
			<account protocol='prpl-sipe'>john.harris@imail.org,co\lpjharri</account>
			<state>busy</state>
		</substatus>
	</status>
	<status name='Auto-Cached' transient='true' created='1380841200' lastused='1380841200' usage_count='1'>
		<state>available</state>
		<substatus>
			<account protocol='prpl-sipe'>john.harris@imail.org,co\lpjharri</account>
			<state>available</state>
		</substatus>
	</status>
	<status name='Auto-Cached' transient='true' created='1380837600' lastused='1380837600' usage_count='1'>
		<state>unavailable</state>
		<substatus>
			<account protocol='prpl-sipe'>john.harris@imail.org,co\lpjharri</account>
			<state>busy</state>
		</substatus>
	</status>
	<status name='Auto-Cached' transient='true' created='1380830400' lastused='1380830400' usage_count='1'>
		<state>available</state>
		<substatus>
			<account protocol='prpl-sipe'>john.harris@imail.org,co\lpjharri</account>
			<state>available</state>
		</substatus>
	</status>
	<status name='Auto-Cached' transient='true' created='1380825000' lastused='1380825000' usage_count='1'>
		<state>unavailable</state>
		<substatus>
			<account protocol='prpl-sipe'>john.harris@imail.org,co\lpjharri</account>
			<state>busy</state>
		</substatus>
	</status>
	<status name='Auto-Cached' transient='true' created='1380736800' lastused='1380736800' usage_count='1'>
		<state>available</state>
		<substatus>
			<account protocol='prpl-sipe'>john.harris@imail.org,co\lpjharri</account>
			<state>available</state>
		</substatus>
	</status>
	<status name='Auto-Cached' transient='true' created='1380735189' lastused='1380735189' usage_count='1'>
		<state>unavailable</state>
		<substatus>
			<account protocol='prpl-sipe'>john.harris@imail.org,co\lpjharri</account>
			<state>busy</state>
		</substatus>
	</status>
	<status name='Auto-Cached' transient='true' created='1380735128' lastused='1380735128' usage_count='1'>
		<state>available</state>
		<substatus>
			<account protocol='prpl-sipe'>john.harris@imail.org,co\lpjharri</account>
			<state>available</state>
		</substatus>
	</status>
	<status name='Auto-Cached' transient='true' created='1380727128' lastused='1380727128' usage_count='1'>
		<state>unavailable</state>
		<substatus>
			<account protocol='prpl-sipe'>john.harris@imail.org,co\lpjharri</account>
			<state>busy</state>
		</substatus>
	</status>
	<status name='Auto-Cached' transient='true' created='1380659400' lastused='1380659400' usage_count='1'>
		<state>available</state>
		<substatus>
			<account protocol='prpl-sipe'>john.harris@imail.org,co\lpjharri</account>
			<state>available</state>
		</substatus>
	</status>
	<status name='Auto-Cached' transient='true' created='1380657600' lastused='1380657600' usage_count='1'>
		<state>unavailable</state>
		<substatus>
			<account protocol='prpl-sipe'>john.harris@imail.org,co\lpjharri</account>
			<state>busy</state>
		</substatus>
	</status>
	<status name='Auto-Cached' transient='true' created='1380124801' lastused='1380124801' usage_count='1'>
		<state>unavailable</state>
		<message>I&amp;apos;m not here right now</message>
		<substatus>
			<account protocol='prpl-sipe'>john.harris@imail.org,co\lpjharri</account>
			<state>busy</state>
			<message>I&amp;apos;m not here right now</message>
		</substatus>
	</status>
	<status name='Auto-Cached' transient='true' created='1380034739' lastused='1380034739' usage_count='1'>
		<state>available</state>
		<message>I&amp;apos;m not here right now</message>
		<substatus>
			<account protocol='prpl-sipe'>john.harris@imail.org,co\lpjharri</account>
			<state>available</state>
			<message>I&amp;apos;m not here right now</message>
		</substatus>
	</status>
	<status name='Auto-Cached' transient='true' created='1379963519' lastused='1379963519' usage_count='1'>
		<state>unavailable</state>
		<message>I&amp;apos;m not here right now</message>
		<substatus>
			<account protocol='prpl-sipe'>john.harris@imail.org,co\lpjharri</account>
			<state>busy</state>
			<message>I&amp;apos;m not here right now</message>
		</substatus>
	</status>
	<status name='Auto-Cached' transient='true' created='1379963458' lastused='1379963458' usage_count='1'>
		<state>available</state>
		<message>I&amp;apos;m not here right now</message>
		<substatus>
			<account protocol='prpl-sipe'>john.harris@imail.org,co\lpjharri</account>
			<state>available</state>
			<message>I&amp;apos;m not here right now</message>
		</substatus>
	</status>
	<status name='Auto-Cached' transient='true' created='1378485531' lastused='1378485531' usage_count='1'>
		<state>available</state>
		<substatus>
			<account protocol='prpl-sipe'>john.harris@imail.org,co\lpjharri</account>
			<state>available</state>
		</substatus>
	</status>
	<status name='Auto-Cached' transient='true' created='1378391252' lastused='1378391252' usage_count='1'>
		<state>available</state>
		<message>I&amp;apos;m not here right now</message>
		<substatus>
			<account protocol='prpl-sipe'>john.harris@imail.org,co\lpjharri</account>
			<state>available</state>
			<message>I&amp;apos;m not here right now</message>
		</substatus>
	</status>
	<status name='Auto-Cached' transient='true' created='1378314744' lastused='1378314744' usage_count='1'>
		<state>unavailable</state>
		<message>I&amp;apos;m not here right now</message>
		<substatus>
			<account protocol='prpl-sipe'>john.harris@imail.org,co\lpjharri</account>
			<state>busy</state>
			<message>I&amp;apos;m not here right now</message>
		</substatus>
	</status>
	<status name='Auto-Cached' transient='true' created='1378314683' lastused='1378314683' usage_count='1'>
		<state>available</state>
		<message>I&amp;apos;m not here right now</message>
		<substatus>
			<account protocol='prpl-sipe'>john.harris@imail.org,co\lpjharri</account>
			<state>available</state>
			<message>I&amp;apos;m not here right now</message>
		</substatus>
	</status>
	<status name='Auto-Cached' transient='true' created='1378309319' lastused='1378309319' usage_count='1'>
		<state>unavailable</state>
		<message>I&amp;apos;m not here right now</message>
		<substatus>
			<account protocol='prpl-sipe'>john.harris@imail.org,co\lpjharri</account>
			<state>busy</state>
			<message>I&amp;apos;m not here right now</message>
		</substatus>
	</status>
	<status name='Auto-Cached' transient='true' created='1377878400' lastused='1377878400' usage_count='1'>
		<state>unavailable</state>
		<message>I&amp;apos;m not here right now</message>
		<substatus>
			<account protocol='prpl-sipe'>john.harris@imail.org,co\lpjharri</account>
			<state>busy</state>
			<message>I&amp;apos;m not here right now</message>
		</substatus>
	</status>
	<status name='Normal' created='1357926702' lastused='1357927005' usage_count='4'>
		<state>available</state>
		<substatus>
			<account protocol='prpl-sipe'>john.harris@imail.org,co\lpjharri</account>
			<state>available</state>
			<message>&lt;font face=&quot;Tahoma&quot;&gt;&lt;font color=&quot;#000000&quot;&gt;He who can no longer pause to wonder and stand rapt in awe, is as good as dead...&lt;/font&gt; -Albert Einstein (Oh well I had a good run anyway)&lt;/font&gt;</message>
		</substatus>
		<substatus>
			<account protocol='prpl-jabber'>harris.johnny@gmail.com</account>
			<state>available</state>
			<message>&lt;font face=&quot;Tahoma&quot;&gt;Hell was full ... So I came back! &amp;gt;:o&lt;/font&gt;</message>
		</substatus>
	</status>
	<status name='Auto-Cached' transient='true' created='1378479642' lastused='0' usage_count='0'>
		<state>away</state>
		<message>I&apos;m not here right now</message>
	</status>
</statuses>
